msgspec_schemaorg/__init__.py
msgspec_schemaorg/base.py
msgspec_schemaorg/enums/__init__.py
msgspec_schemaorg/enums/intangible/ActionStatusType.py
msgspec_schemaorg/enums/intangible/AdultOrientedEnumeration.py
msgspec_schemaorg/enums/intangible/BoardingPolicyType.py
msgspec_schemaorg/enums/intangible/BodyMeasurementTypeEnumeration.py
msgspec_schemaorg/enums/intangible/BookFormatType.py
msgspec_schemaorg/enums/intangible/CarUsageType.py
msgspec_schemaorg/enums/intangible/CertificationStatusEnumeration.py
msgspec_schemaorg/enums/intangible/ContactPointOption.py
msgspec_schemaorg/enums/intangible/DayOfWeek.py
msgspec_schemaorg/enums/intangible/DeliveryMethod.py
msgspec_schemaorg/enums/intangible/DigitalDocumentPermissionType.py
msgspec_schemaorg/enums/intangible/DigitalPlatformEnumeration.py
msgspec_schemaorg/enums/intangible/DriveWheelConfigurationValue.py
msgspec_schemaorg/enums/intangible/DrugCostCategory.py
msgspec_schemaorg/enums/intangible/DrugPregnancyCategory.py
msgspec_schemaorg/enums/intangible/DrugPrescriptionStatus.py
msgspec_schemaorg/enums/intangible/EUEnergyEfficiencyEnumeration.py
msgspec_schemaorg/enums/intangible/EnergyStarEnergyEfficiencyEnumeration.py
msgspec_schemaorg/enums/intangible/EventAttendanceModeEnumeration.py
msgspec_schemaorg/enums/intangible/EventStatusType.py
msgspec_schemaorg/enums/intangible/FulfillmentTypeEnumeration.py
msgspec_schemaorg/enums/intangible/GameAvailabilityEnumeration.py
msgspec_schemaorg/enums/intangible/GamePlayMode.py
msgspec_schemaorg/enums/intangible/GameServerStatus.py
msgspec_schemaorg/enums/intangible/GenderType.py
msgspec_schemaorg/enums/intangible/GovernmentBenefitsType.py
msgspec_schemaorg/enums/intangible/HealthAspectEnumeration.py
msgspec_schemaorg/enums/intangible/IPTCDigitalSourceEnumeration.py
msgspec_schemaorg/enums/intangible/IncentiveQualifiedExpenseType.py
msgspec_schemaorg/enums/intangible/IncentiveStatus.py
msgspec_schemaorg/enums/intangible/IncentiveType.py
msgspec_schemaorg-0.2.1.dist-info/LICENSE
msgspec_schemaorg-0.2.1.dist-info/METADATA
msgspec_schemaorg-0.2.1.dist-info/WHEEL
msgspec_schemaorg-0.2.1.dist-info/RECORD
