Metadata-Version: 2.3
Name: msgspec-schemaorg
Version: 0.2.1
Summary: Generate Python msgspec.Struct classes from the Schema.org vocabulary
License: MIT
Author: Michael Deeb
Author-email: michael.f.deeb@gmail.com
Requires-Python: >=3.10
Classifier: Programming Language :: Python :: 3
Classifier: License :: OSI Approved :: MIT License
Classifier: Operating System :: OS Independent
Provides-Extra: dev
Requires-Dist: build ; extra == "dev"
Requires-Dist: msgspec (>=0.19.0)
Requires-Dist: pytest ; extra == "dev"
Requires-Dist: requests (>=2.28.0)
Requires-Dist: twine ; extra == "dev"
Project-URL: Bug Tracker, https://github.com/mikewolfd/msgspec-schemaorg/issues
Project-URL: Homepage, https://github.com/mikewolfd/msgspec-schemaorg
